{
    "metadata": {
        "code": 200,
        "message": "Ok"
    },
    "response": {
        "data": {
            "kode_rs": "6472123",
            "kelas_rs": "C",
            "kelas_rawat": 3,
            "kode_tarif": "",
            "jenis_rawat": 2,
            "tgl_masuk": "00\/00\/0000",
            "tgl_pulang": "00\/00\/0000",
            "cara_masuk": null,
            "tgl_lahir": "21\/12\/2014",
            "berat_lahir": "0",
            "gender": 2,
            "discharge_status": 5,
            "diagnosa": "",
            "procedure": "",
            "diagnosa_inagrouper": "",
            "procedure_inagrouper": "",
            "adl_sub_acute": 0,
            "adl_chronic": 0,
            "tarif_rs": {
                "prosedur_non_bedah": 0,
                "prosedur_bedah": 0,
                "konsultasi": 0,
                "tenaga_ahli": 0,
                "keperawatan": 0,
                "penunjang": 0,
                "radiologi": 0,
                "laboratorium": 0,
                "pelayanan_darah": 0,
                "rehabilitasi": 0,
                "kamar": 0,
                "rawat_intensif": 0,
                "obat": 0,
                "obat_kronis": 0,
                "obat_kemoterapi": 0,
                "alkes": 0,
                "bmhp": 0,
                "sewa_alat": 0
            },
            "sistole": "",
            "diastole": "",
            "los": "0",
            "icu_indikator": 0,
            "icu_los": "0",
            "ventilator_hour": "0",
            "upgrade_class_ind": "0",
            "upgrade_class_class": "",
            "upgrade_class_los": "0",
            "add_payment_pct": "0.0",
            "add_payment_amt": "0",
            "upgrade_class_payor": null,
            "nama_pasien": "RISKI MAULANI",
            "nomor_rm": "999999",
            "umur_tahun": 0,
            "umur_hari": null,
            "tarif_poli_eks": "0",
            "dializer_single_use": "0",
            "nama_dokter": "",
            "nomor_sep": "0302R1100825V999995",
            "nomor_kartu": "0000123456700",
            "payor_id": "3",
            "payor_nm": "JKN",
            "coder_nm": "",
            "coder_nik": "",
            "patient_id": "5",
            "admission_id": "2",
            "hospital_admission_id": "29",
            "grouping_count": "0",
            "grouper": {
                "response_inacbg": null,
                "response_idrg": {
                    "mdc_number": "",
                    "mdc_description": "",
                    "drg_code": "",
                    "drg_description": ""
                }
            },
            "kemenkes_dc_status_cd": "unsent",
            "kemenkes_dc_sent_dttm": "-",
            "bpjs_dc_status_cd": "unsent",
            "bpjs_dc_sent_dttm": "-",
            "klaim_status_cd": "normal",
            "bpjs_klaim_status_cd": "-",
            "bpjs_klaim_status_nm": "-"
        }
    }
}
